pubmed_citation/__init__.py
pubmed_citation/cli.py
pubmed_citation/models.py
pubmed_citation/navigate.py
pubmed_citation/scaffold.py
pubmed_citation-0.1.1.dist-info/METADATA
pubmed_citation-0.1.1.dist-info/WHEEL
pubmed_citation-0.1.1.dist-info/entry_points.txt
pubmed_citation-0.1.1.dist-info/top_level.txt
pubmed_citation-0.1.1.dist-info/RECORD
