Metadata-Version: 2.4
Name: pubmed-citation
Version: 0.1.1
Summary: A tool for collecting citation data from PubMed and analyzing author relationships
Home-page: https://github.com/yourusername/pubmed-citation
Author: Your Name
Author-email: your.email@example.com
Project-URL: Bug Tracker, https://github.com/yourusername/pubmed-citation/issues
Classifier: Programming Language :: Python :: 3
Classifier: License :: OSI Approved :: MIT License
Classifier: Operating System :: OS Independent
Classifier: Topic :: Scientific/Engineering :: Bio-Informatics
Classifier: Topic :: Scientific/Engineering :: Information Analysis
Requires-Python: >=3.6
Requires-Dist: requests>=2.25.0
Dynamic: author
Dynamic: author-email
Dynamic: classifier
Dynamic: description
Dynamic: description-content-type
Dynamic: home-page
Dynamic: project-url
Dynamic: requires-dist
Dynamic: requires-python
Dynamic: summary
